py_rattler-0.22.0.dist-info/METADATA
py_rattler-0.22.0.dist-info/WHEEL
rattler/__init__.py
rattler/channel/__init__.py
rattler/channel/channel.py
rattler/channel/channel_config.py
rattler/channel/channel_priority.py
rattler/exceptions.py
rattler/explicit_environment/__init__.py
rattler/explicit_environment/environment.py
rattler/index/__init__.py
rattler/index/index.py
rattler/install/__init__.py
rattler/install/installer.py
rattler/lock/__init__.py
rattler/lock/channel.py
rattler/lock/environment.py
rattler/lock/hash.py
rattler/lock/lock_file.py
rattler/lock/package.py
rattler/match_spec/__init__.py
rattler/match_spec/match_spec.py
rattler/match_spec/nameless_match_spec.py
rattler/networking/__init__.py
rattler/networking/client.py
rattler/networking/fetch_repo_data.py
rattler/networking/middleware.py
rattler/package/__init__.py
rattler/package/about_json.py
rattler/package/index_json.py
rattler/package/no_arch_type.py
rattler/package/package_name.py
rattler/package/package_name_matcher.py
rattler/package/paths_json.py
rattler/package/run_exports_json.py
rattler/package_streaming/__init__.py
rattler/platform/__init__.py
rattler/platform/arch.py
rattler/platform/platform.py
rattler/prefix/__init__.py
rattler/prefix/prefix_paths.py
rattler/prefix/prefix_record.py
rattler/pty/__init__.py
rattler/pty/pty_process.py
rattler/pty/pty_session.py
rattler/py.typed
rattler/rattler.abi3.so
rattler/repo_data/__init__.py
rattler/repo_data/gateway.py
rattler/repo_data/package_record.py
rattler/repo_data/patch_instructions.py
rattler/repo_data/record.py
rattler/repo_data/repo_data.py
rattler/repo_data/source.py
rattler/repo_data/sparse.py
rattler/shell/__init__.py
rattler/shell/shell.py
rattler/solver/__init__.py
rattler/solver/solver.py
rattler/utils/rattler_version.py
rattler/version/__init__.py
rattler/version/version.py
rattler/version/version_spec.py
rattler/version/with_source.py
rattler/virtual_package/__init__.py
rattler/virtual_package/generic.py
rattler/virtual_package/virtual_package.py
py_rattler-0.22.0.dist-info/RECORD
