Metadata-Version: 2.4
Name: py-rattler
Version: 0.22.0
Classifier: Development Status :: 3 - Alpha
Classifier: Intended Audience :: Developers
Classifier: License :: OSI Approved :: BSD License
Classifier: Programming Language :: Rust
Classifier: Programming Language :: Python :: Implementation :: CPython
Classifier: Programming Language :: Python :: Implementation :: PyPy
Classifier: Typing :: Typed
Summary: A blazing fast library to work with the conda ecosystem
Author-email: Bas Zalmstra <zalmstra.bas@gmail.com>, Tarun Pratap Singh <pratapsinghtarun9@gmail.com>
License-Expression: BSD-3-Clause
Requires-Python: >=3.8
Project-URL: Homepage, https://github.com/conda/rattler
Project-URL: Documentation, https://conda.github.io/rattler/py-rattler/
Project-URL: Repository, https://github.com/conda/rattler
Project-URL: Issues, https://github.com/conda/rattler/labels/python-bindings
